[{"id": "1755230654323-0", "data": {"timestamp": "2025-08-15T04:04:14.322399", "price": 245.84, "volume": 849, "symbol": "AAPL"}}, {"id": "1755230655326-0", "data": {"timestamp": "2025-08-15T04:04:15.326590", "price": 172.95, "volume": 900, "symbol": "GOOG"}}, {"id": "1755230656333-0", "data": {"timestamp": "2025-08-15T04:04:16.333308", "price": 284.32, "volume": 326, "symbol": "GOOG"}}, {"id": "1755230657337-0", "data": {"timestamp": "2025-08-15T04:04:17.337132", "price": 321.93, "volume": 47, "symbol": "RELIANCE"}}, {"id": "1755230658344-0", "data": {"timestamp": "2025-08-15T04:04:18.343943", "price": 303.43, "volume": 119, "symbol": "AAPL"}}, {"id": "1755230659350-0", "data": {"timestamp": "2025-08-15T04:04:19.349779", "price": 196.05, "volume": 492, "symbol": "TSLA"}}, {"id": "1755230660356-0", "data": {"timestamp": "2025-08-15T04:04:20.355625", "price": 250.64, "volume": 610, "symbol": "AAPL"}}, {"id": "1755230661363-0", "data": {"timestamp": "2025-08-15T04:04:21.362842", "price": 315.6, "volume": 390, "symbol": "AAPL"}}, {"id": "1755230662385-0", "data": {"timestamp": "2025-08-15T04:04:22.385093", "price": 105.02, "volume": 151, "symbol": "INFY"}}, {"id": "1755230663397-0", "data": {"timestamp": "2025-08-15T04:04:23.397146", "price": 297.54, "volume": 155, "symbol": "GOOG"}}, {"id": "1755230664405-0", "data": {"timestamp": "2025-08-15T04:04:24.405238", "price": 377.56, "volume": 490, "symbol": "GOOG"}}, {"id": "1755230665409-0", "data": {"timestamp": "2025-08-15T04:04:25.409202", "price": 441.06, "volume": 386, "symbol": "INFY"}}, {"id": "1755230666423-0", "data": {"timestamp": "2025-08-15T04:04:26.423423", "price": 359.49, "volume": 162, "symbol": "TSLA"}}, {"id": "1755230667431-0", "data": {"timestamp": "2025-08-15T04:04:27.431405", "price": 374.84, "volume": 853, "symbol": "TSLA"}}, {"id": "1755230668436-0", "data": {"timestamp": "2025-08-15T04:04:28.435911", "price": 193.65, "volume": 933, "symbol": "RELIANCE"}}, {"id": "1755230669440-0", "data": {"timestamp": "2025-08-15T04:04:29.440215", "price": 320.9, "volume": 285, "symbol": "RELIANCE"}}, {"id": "1755230670448-0", "data": {"timestamp": "2025-08-15T04:04:30.448001", "price": 355.94, "volume": 713, "symbol": "INFY"}}, {"id": "1755230671456-0", "data": {"timestamp": "2025-08-15T04:04:31.455254", "price": 152.18, "volume": 132, "symbol": "INFY"}}, {"id": "1755230672463-0", "data": {"timestamp": "2025-08-15T04:04:32.463396", "price": 208.22, "volume": 335, "symbol": "GOOG"}}, {"id": "1755230673469-0", "data": {"timestamp": "2025-08-15T04:04:33.468635", "price": 283.21, "volume": 76, "symbol": "INFY"}}, {"id": "1755230674474-0", "data": {"timestamp": "2025-08-15T04:04:34.472971", "price": 274.37, "volume": 43, "symbol": "AAPL"}}, {"id": "1755230675481-0", "data": {"timestamp": "2025-08-15T04:04:35.481317", "price": 463.91, "volume": 498, "symbol": "AAPL"}}, {"id": "1755230676489-0", "data": {"timestamp": "2025-08-15T04:04:36.488763", "price": 421.83, "volume": 32, "symbol": "RELIANCE"}}, {"id": "1755230677493-0", "data": {"timestamp": "2025-08-15T04:04:37.493110", "price": 337.97, "volume": 803, "symbol": "RELIANCE"}}, {"id": "1755230678497-0", "data": {"timestamp": "2025-08-15T04:04:38.497496", "price": 399.89, "volume": 573, "symbol": "RELIANCE"}}, {"id": "1755230679503-0", "data": {"timestamp": "2025-08-15T04:04:39.503515", "price": 379.61, "volume": 825, "symbol": "AAPL"}}, {"id": "1755230680510-0", "data": {"timestamp": "2025-08-15T04:04:40.510589", "price": 412.67, "volume": 365, "symbol": "INFY"}}, {"id": "1755230681513-0", "data": {"timestamp": "2025-08-15T04:04:41.513239", "price": 423.88, "volume": 528, "symbol": "AAPL"}}, {"id": "1755230682521-0", "data": {"timestamp": "2025-08-15T04:04:42.521114", "price": 416.24, "volume": 376, "symbol": "AAPL"}}, {"id": "1755230683525-0", "data": {"timestamp": "2025-08-15T04:04:43.525499", "price": 196.76, "volume": 184, "symbol": "INFY"}}, {"id": "1755230684531-0", "data": {"timestamp": "2025-08-15T04:04:44.530861", "price": 238.75, "volume": 786, "symbol": "GOOG"}}, {"id": "1755230685535-0", "data": {"timestamp": "2025-08-15T04:04:45.534970", "price": 340.1, "volume": 246, "symbol": "INFY"}}, {"id": "1755230686540-0", "data": {"timestamp": "2025-08-15T04:04:46.540466", "price": 161.01, "volume": 986, "symbol": "RELIANCE"}}, {"id": "1755230687543-0", "data": {"timestamp": "2025-08-15T04:04:47.543020", "price": 110.19, "volume": 988, "symbol": "TSLA"}}, {"id": "1755230688546-0", "data": {"timestamp": "2025-08-15T04:04:48.546376", "price": 202.2, "volume": 898, "symbol": "RELIANCE"}}, {"id": "1755230689555-0", "data": {"timestamp": "2025-08-15T04:04:49.554677", "price": 374.01, "volume": 627, "symbol": "INFY"}}, {"id": "1755230690562-0", "data": {"timestamp": "2025-08-15T04:04:50.562434", "price": 243.52, "volume": 686, "symbol": "INFY"}}, {"id": "1755230691569-0", "data": {"timestamp": "2025-08-15T04:04:51.568876", "price": 253.18, "volume": 456, "symbol": "TSLA"}}, {"id": "1755230692576-0", "data": {"timestamp": "2025-08-15T04:04:52.576208", "price": 347.69, "volume": 154, "symbol": "AAPL"}}, {"id": "1755230693584-0", "data": {"timestamp": "2025-08-15T04:04:53.583616", "price": 383.43, "volume": 395, "symbol": "RELIANCE"}}, {"id": "1755230694590-0", "data": {"timestamp": "2025-08-15T04:04:54.590699", "price": 423.55, "volume": 270, "symbol": "GOOG"}}, {"id": "1755230695609-0", "data": {"timestamp": "2025-08-15T04:04:55.608796", "price": 148.37, "volume": 869, "symbol": "RELIANCE"}}, {"id": "1755230696618-0", "data": {"timestamp": "2025-08-15T04:04:56.618149", "price": 156.07, "volume": 49, "symbol": "TSLA"}}, {"id": "1755230697630-0", "data": {"timestamp": "2025-08-15T04:04:57.629820", "price": 444.04, "volume": 48, "symbol": "INFY"}}, {"id": "1755230698634-0", "data": {"timestamp": "2025-08-15T04:04:58.633875", "price": 498.61, "volume": 133, "symbol": "TSLA"}}, {"id": "1755230699641-0", "data": {"timestamp": "2025-08-15T04:04:59.639058", "price": 104.24, "volume": 422, "symbol": "AAPL"}}, {"id": "1755230700647-0", "data": {"timestamp": "2025-08-15T04:05:00.646799", "price": 395.51, "volume": 576, "symbol": "INFY"}}, {"id": "1755230701650-0", "data": {"timestamp": "2025-08-15T04:05:01.650374", "price": 423.45, "volume": 313, "symbol": "GOOG"}}, {"id": "1755230702658-0", "data": {"timestamp": "2025-08-15T04:05:02.657313", "price": 369.77, "volume": 153, "symbol": "AAPL"}}, {"id": "1755230703661-0", "data": {"timestamp": "2025-08-15T04:05:03.661066", "price": 471.4, "volume": 110, "symbol": "TSLA"}}, {"id": "1755230704666-0", "data": {"timestamp": "2025-08-15T04:05:04.666639", "price": 314.06, "volume": 270, "symbol": "GOOG"}}, {"id": "1755230705670-0", "data": {"timestamp": "2025-08-15T04:05:05.670835", "price": 411.86, "volume": 793, "symbol": "AAPL"}}, {"id": "1755230706675-0", "data": {"timestamp": "2025-08-15T04:05:06.674965", "price": 446.16, "volume": 290, "symbol": "INFY"}}, {"id": "1755230707681-0", "data": {"timestamp": "2025-08-15T04:05:07.680792", "price": 459.59, "volume": 916, "symbol": "AAPL"}}, {"id": "1755230708684-0", "data": {"timestamp": "2025-08-15T04:05:08.684042", "price": 385.21, "volume": 347, "symbol": "AAPL"}}, {"id": "1755230709694-0", "data": {"timestamp": "2025-08-15T04:05:09.694008", "price": 305.27, "volume": 592, "symbol": "TSLA"}}, {"id": "1755230710702-0", "data": {"timestamp": "2025-08-15T04:05:10.701829", "price": 212.68, "volume": 18, "symbol": "INFY"}}, {"id": "1755230711709-0", "data": {"timestamp": "2025-08-15T04:05:11.709314", "price": 422.05, "volume": 210, "symbol": "AAPL"}}, {"id": "1755230712715-0", "data": {"timestamp": "2025-08-15T04:05:12.715227", "price": 398.71, "volume": 214, "symbol": "INFY"}}, {"id": "1755230713723-0", "data": {"timestamp": "2025-08-15T04:05:13.718568", "price": 390.84, "volume": 641, "symbol": "INFY"}}, {"id": "1755230714726-0", "data": {"timestamp": "2025-08-15T04:05:14.726362", "price": 307.6, "volume": 630, "symbol": "TSLA"}}, {"id": "1755230715733-0", "data": {"timestamp": "2025-08-15T04:05:15.733498", "price": 390.48, "volume": 171, "symbol": "RELIANCE"}}, {"id": "1755230716741-0", "data": {"timestamp": "2025-08-15T04:05:16.741253", "price": 371.49, "volume": 886, "symbol": "RELIANCE"}}, {"id": "1755230717747-0", "data": {"timestamp": "2025-08-15T04:05:17.747379", "price": 462.76, "volume": 829, "symbol": "RELIANCE"}}, {"id": "1755230718751-0", "data": {"timestamp": "2025-08-15T04:05:18.750692", "price": 185.81, "volume": 462, "symbol": "RELIANCE"}}, {"id": "1755230719754-0", "data": {"timestamp": "2025-08-15T04:05:19.754068", "price": 251.94, "volume": 327, "symbol": "TSLA"}}, {"id": "1755230720758-0", "data": {"timestamp": "2025-08-15T04:05:20.757688", "price": 468.27, "volume": 27, "symbol": "INFY"}}]